MDIO/controller/controller.v
`timescale 1ns / 1ps
module controller(
    input wire clk,
    input wire reset,
    input wire mdio_out,
    input wire mdio_oe,
    output reg mdio_done,
    output reg [15:0] mdio_in,
    output reg [4:0] addr,
    output reg [15:0] wr_data,
    input wire [15:0] rd_data,
    output reg wr_stb
);

// Declaración de parámetros y estados
parameter IDLE = 3'b000, READ = 3'b001, WRITE = 3'b010, SEND_DATA = 3'b011, RECEIVE_DATA = 3'b100;
reg [2:0] state, next_state;
reg [4:0] bit_counter;
reg [31:0] shift_reg;

// Lógica de estado siguiente
always @(posedge clk or posedge reset) begin
    if (reset) begin
        state <= IDLE;
    end else begin
        state <= next_state;
    end
end

// Lógica de salida y transiciones de estado
always @(posedge clk) begin
    case (state)
        IDLE: begin
            mdio_done <= 1'b0;
            wr_stb <= 1'b0;
            bit_counter <= 5'd0;
            shift_reg <= 32'd0;
            if (mdio_oe) begin
                next_state <= (mdio_out) ? WRITE : READ;
            end else begin
                next_state <= IDLE;
            end
        end
        READ: begin
            if (bit_counter == 5'd15) begin
                next_state <= RECEIVE_DATA;
                mdio_in <= 16'd0; // Inicializar mdio_in
            end else begin
                shift_reg <= {shift_reg[30:0], mdio_out};
                bit_counter <= bit_counter + 1'b1;
            end
        end
        WRITE: begin
            if (bit_counter == 5'd31) begin
                next_state <= SEND_DATA;
            end else begin
                shift_reg <= {shift_reg[30:0], mdio_out};
                bit_counter <= bit_counter + 1'b1;
            end
        end
        SEND_DATA: begin
            addr <= shift_reg[20:16];
            wr_data <= shift_reg[15:0];
            wr_stb <= 1'b1;
            mdio_done <= 1'b1;
            next_state <= IDLE;
        end
        RECEIVE_DATA: begin
            mdio_in <= {mdio_in[14:0], 1'b0}; // Desplazar mdio_in
            bit_counter <= bit_counter + 1'b1;
            if (bit_counter == 5'd31) begin
                mdio_done <= 1'b1;
                next_state <= IDLE;
            end
        end
    endcase
end

endmodule

MDIO/controller/controller_tb.v
`timescale 1ns / 1ps
`include "controller/controller.v"

module controller_tb;
    // Entradas del controlador
    reg clk, reset;
    reg mdio_out, mdio_oe;
    reg [15:0] rd_data;

    // Salidas del controlador
    wire mdio_done;
    wire [15:0] mdio_in;
    wire [4:0] addr;
    wire [15:0] wr_data;
    wire wr_stb;

    // Instancia del módulo controlador
    controller controller_inst(
        .clk(clk),
        .reset(reset),
        .mdio_out(mdio_out),
        .mdio_oe(mdio_oe),
        .mdio_done(mdio_done),
        .mdio_in(mdio_in),
        .addr(addr),
        .wr_data(wr_data),
        .rd_data(rd_data),
        .wr_stb(wr_stb)
    );

    // Inicialización de señales
    initial begin
        $dumpfile("sim.vcd");
        $dumpvars(0, controller_tb);
        clk = 0;
        reset = 1;
        mdio_out = 0;
        mdio_oe = 0;
        rd_data = 0;
        #10 reset = 0;
        #10 reset = 1;
    end

    // Generación de reloj
    always #5 clk = ~clk;

    // Tarea para imprimir el estado de las señales
    task print_signals;
        begin
            $display("Time: %0t", $time);
            $display("State: %b, mdio_done: %b, mdio_in: %h, addr: %d, wr_data: %h, wr_stb: %b",
                     controller_inst.state, mdio_done, mdio_in, addr, wr_data, wr_stb);
        end
    endtask

    // Pruebas según el protocolo MDIO cláusula 22 (IEEE 802.3)
    initial begin
        // Prueba 1: Inicialización y reset
        print_signals;

        // Esperar un tiempo para permitir que el controlador se reinicie
        #100;

        // Prueba 2: Transacción de Escritura válida
        mdio_oe = 1;
        mdio_out = 1; // Código de operación = 01 (Escritura)
        #10;
        mdio_out = 0; // Reservado
        repeat (5) #10 mdio_out = 0; // Reservado
        mdio_out = 4'b0001; // Dirección del PHY = 1
        #10;
        mdio_out = 5'b00101; // Dirección del Registro = 5
        #10;
        mdio_out = 16'habcd; // Datos de Escritura
        repeat (16) #10 mdio_out = ~mdio_out;
        #100; // Esperar un tiempo para que la transacción se complete
        print_signals;

        // Prueba 3: Transacción de Lectura válida
        mdio_oe = 1;
        mdio_out = 0; // Código de operación = 00 (Lectura)
        #10;
        mdio_out = 0; // Reservado
        repeat (5) #10 mdio_out = 0; // Reservado
        mdio_out = 4'b0010; // Dirección del PHY = 2
        #10;
        mdio_out = 5'b01000; // Dirección del Registro = 8
        #10;
        mdio_out = 16'h0000; // Sin usar para Lectura
        repeat (16) #10 mdio_out = ~mdio_out;
        rd_data = 16'hfeed; // Datos de Lectura
        #100; // Esperar un tiempo para que la transacción se complete
        print_signals;

        // Prueba 4: Transacción de Escritura inválida (dirección de registro fuera de rango)
        mdio_oe = 1;
        mdio_out = 1; // Código de operación = 01 (Escritura)
        #10;
        mdio_out = 0; // Reservado
        repeat (5) #10 mdio_out = 0; // Reservado
        mdio_out = 4'b0011; // Dirección del PHY = 3
        #10;
        mdio_out = 5'b11111; // Dirección del Registro = 31 (fuera de rango)
        #10;
        mdio_out = 16'hffff; // Datos de Escritura
        repeat (16) #10 mdio_out = ~mdio_out;
        #100; // Esperar un tiempo para que la transacción se complete
        print_signals;

        // Prueba 5: Transacción de Lectura inválida (dirección de PHY fuera de rango)
        mdio_oe = 1;
        mdio_out = 0; // Código de operación = 00 (Lectura)
        #10;
        mdio_out = 0; // Reservado
        repeat (5) #10 mdio_out = 0; // Reservado
        mdio_out = 4'b1111; // Dirección del PHY = 15 (fuera de rango)
        #10;
        mdio_out = 5'b00111; // Dirección del Registro = 7
        #10;
        mdio_out = 16'h0000; // Sin usar para Lectura
        repeat (16) #10 mdio_out = ~mdio_out;
        rd_data = 16'hcafe; // Datos de Lectura
        #100; // Esperar un tiempo para que la transacción se complete
        print_signals;

        // Esperar un tiempo adicional para permitir que se complete la simulación
        #1000;
        $finish;
    end

endmodule

MDIO/sim.vcd
$date
	Tue Jun 11 00:41:11 2024
$end
$version
	Icarus Verilog
$end
$timescale
	1ps
$end
$scope module controller_tb $end
$var wire 1 ! wr_stb $end
$var wire 16 " wr_data [15:0] $end
$var wire 16 # mdio_in [15:0] $end
$var wire 1 $ mdio_done $end
$var wire 5 % addr [4:0] $end
$var reg 1 & clk $end
$var reg 1 ' mdio_oe $end
$var reg 1 ( mdio_out $end
$var reg 16 ) rd_data [15:0] $end
$var reg 1 * reset $end
$scope module controller_inst $end
$var wire 1 & clk $end
$var wire 1 ' mdio_oe $end
$var wire 1 ( mdio_out $end
$var wire 16 + rd_data [15:0] $end
$var wire 1 * reset $end
$var reg 5 , addr [4:0] $end
$var reg 5 - bit_counter [4:0] $end
$var reg 1 $ mdio_done $end
$var reg 16 . mdio_in [15:0] $end
$var reg 3 / next_state [2:0] $end
$var reg 32 0 shift_reg [31:0] $end
$var reg 3 1 state [2:0] $end
$var reg 16 2 wr_data [15:0] $end
$var reg 1 ! wr_stb $end
$upscope $end
$scope task print_signals $end
$upscope $end
$upscope $end
$enddefinitions $end
#0
$dumpvars
bx 2
b0 1
bx 0
bx /
bx .
bx -
bx ,
b0 +
1*
b0 )
0(
0'
0&
bx %
x$
bx #
bx "
x!
$end
#5000
b0 /
b0 0
b0 -
0!
0$
1&
#10000
0&
0*
#15000
1&
#20000
0&
1*
#25000
1&
#30000
0&
#35000
1&
#40000
0&
#45000
1&
#50000
0&
#55000
1&
#60000
0&
#65000
1&
#70000
0&
#75000
1&
#80000
0&
#85000
1&
#90000
0&
#95000
1&
#100000
0&
1(
1'
#105000
b10 /
1&
#110000
0&
0(
#115000
b1 /
1&
#120000
0&
#125000
1&
#130000
0&
#135000
1&
#140000
0&
#145000
1&
#150000
0&
#155000
1&
#160000
0&
1(
#165000
b10 /
1&
#170000
0&
#175000
1&
#180000
0&
#185000
1&
#190000
0&
0(
#195000
b1 /
1&
#200000
0&
1(
#205000
b10 /
1&
#210000
0&
0(
#215000
b1 /
1&
#220000
0&
1(
#225000
b10 /
1&
#230000
0&
0(
#235000
b1 /
1&
#240000
0&
1(
#245000
b10 /
1&
#250000
0&
0(
#255000
b1 /
1&
#260000
0&
1(
#265000
b10 /
1&
#270000
0&
0(
#275000
b1 /
1&
#280000
0&
1(
#285000
b10 /
1&
#290000
0&
0(
#295000
b1 /
1&
#300000
0&
1(
#305000
b10 /
1&
#310000
0&
0(
#315000
b1 /
1&
#320000
0&
1(
#325000
b10 /
1&
#330000
0&
0(
#335000
b1 /
1&
#340000
0&
1(
#345000
b10 /
1&
#350000
0&
#355000
1&
#360000
0&
#365000
1&
#370000
0&
#375000
1&
#380000
0&
#385000
1&
#390000
0&
#395000
1&
#400000
0&
#405000
1&
#410000
0&
#415000
1&
#420000
0&
#425000
1&
#430000
0&
#435000
1&
#440000
0&
0(
#445000
b1 /
1&
#450000
0&
#455000
1&
#460000
0&
#465000
1&
#470000
0&
#475000
1&
#480000
0&
#485000
1&
#490000
0&
#495000
1&
#500000
0&
#505000
1&
#510000
0&
#515000
1&
#520000
0&
#525000
1&
#530000
0&
1(
#535000
b10 /
1&
#540000
0&
0(
#545000
b1 /
1&
#550000
0&
1(
#555000
b10 /
1&
#560000
0&
0(
#565000
b1 /
1&
#570000
0&
1(
#575000
b10 /
1&
#580000
0&
0(
#585000
b1 /
1&
#590000
0&
1(
#595000
b10 /
1&
#600000
0&
0(
#605000
b1 /
1&
#610000
0&
1(
#615000
b10 /
1&
#620000
0&
0(
#625000
b1 /
1&
#630000
0&
1(
#635000
b10 /
1&
#640000
0&
0(
#645000
b1 /
1&
#650000
0&
1(
#655000
b10 /
1&
#660000
0&
0(
#665000
b1 /
1&
#670000
0&
1(
#675000
b10 /
1&
#680000
0&
b1111111011101101 )
b1111111011101101 +
0(
#685000
b1 /
1&
#690000
0&
#695000
1&
#700000
0&
#705000
1&
#710000
0&
#715000
1&
#720000
0&
#725000
1&
#730000
0&
#735000
1&
#740000
0&
#745000
1&
#750000
0&
#755000
1&
#760000
0&
#765000
1&
#770000
0&
#775000
1&
#780000
0&
1(
#785000
b10 /
1&
#790000
0&
0(
#795000
b1 /
1&
#800000
0&
#805000
1&
#810000
0&
#815000
1&
#820000
0&
#825000
1&
#830000
0&
#835000
1&
#840000
0&
1(
#845000
b10 /
1&
#850000
0&
#855000
1&
#860000
0&
#865000
1&
#870000
0&
0(
#875000
b1 /
1&
#880000
0&
1(
#885000
b10 /
1&
#890000
0&
0(
#895000
b1 /
1&
#900000
0&
1(
#905000
b10 /
1&
#910000
0&
0(
#915000
b1 /
1&
#920000
0&
1(
#925000
b10 /
1&
#930000
0&
0(
#935000
b1 /
1&
#940000
0&
1(
#945000
b10 /
1&
#950000
0&
0(
#955000
b1 /
1&
#960000
0&
1(
#965000
b10 /
1&
#970000
0&
0(
#975000
b1 /
1&
#980000
0&
1(
#985000
b10 /
1&
#990000
0&
0(
#995000
b1 /
1&
#1000000
0&
1(
#1005000
b10 /
1&
#1010000
0&
0(
#1015000
b1 /
1&
#1020000
0&
1(
#1025000
b10 /
1&
#1030000
0&
#1035000
1&
#1040000
0&
#1045000
1&
#1050000
0&
#1055000
1&
#1060000
0&
#1065000
1&
#1070000
0&
#1075000
1&
#1080000
0&
#1085000
1&
#1090000
0&
#1095000
1&
#1100000
0&
#1105000
1&
#1110000
0&
#1115000
1&
#1120000
0&
0(
#1125000
b1 /
1&
#1130000
0&
#1135000
1&
#1140000
0&
#1145000
1&
#1150000
0&
#1155000
1&
#1160000
0&
#1165000
1&
#1170000
0&
#1175000
1&
#1180000
0&
1(
#1185000
b10 /
1&
#1190000
0&
#1195000
1&
#1200000
0&
0(
#1205000
b1 /
1&
#1210000
0&
1(
#1215000
b10 /
1&
#1220000
0&
0(
#1225000
b1 /
1&
#1230000
0&
1(
#1235000
b10 /
1&
#1240000
0&
0(
#1245000
b1 /
1&
#1250000
0&
1(
#1255000
b10 /
1&
#1260000
0&
0(
#1265000
b1 /
1&
#1270000
0&
1(
#1275000
b10 /
1&
#1280000
0&
0(
#1285000
b1 /
1&
#1290000
0&
1(
#1295000
b10 /
1&
#1300000
0&
0(
#1305000
b1 /
1&
#1310000
0&
1(
#1315000
b10 /
1&
#1320000
0&
0(
#1325000
b1 /
1&
#1330000
0&
1(
#1335000
b10 /
1&
#1340000
0&
0(
#1345000
b1 /
1&
#1350000
0&
1(
#1355000
b10 /
1&
#1360000
0&
b1100101011111110 )
b1100101011111110 +
0(
#1365000
b1 /
1&
