MDIO/controller/controller.v
`timescale 1ns / 1ps

module mdio_controller(
    input wire clk,
    input wire reset,
    input wire mdio_in,
    output reg mdio_out,
    output reg mdio_oe,
    output reg mdc,
    input wire [4:0] phy_addr,
    input wire [4:0] reg_addr,
    input wire [15:0] write_data,
    output reg [15:0] read_data,
    input wire start,
    input wire operation, // 0 para escritura, 1 para lectura
    output reg busy
);

// Estados del controlador MDIO
localparam IDLE = 0,
           PREPARE = 1,
           SEND = 2,
           RECEIVE = 3,
           FINISH = 4;

integer state = IDLE, next_state = IDLE;
integer bit_count; // Contador de bits enviados/recibidos
reg [31:0] shift_reg; // Registro de desplazamiento para la trama MDIO

// Generación del reloj MDIO (MDC)
always @(posedge clk) begin
    if (reset) begin
        mdc <= 0;
    end else begin
        mdc <= ~mdc; // Toggle MDC en cada ciclo de reloj
    end
end

// Lógica de control de estado
always @(posedge clk) begin
    if (reset) begin
        state <= IDLE;
        busy <= 0;
        mdio_oe <= 0;
        mdio_out <= 0;
        read_data <= 0;
        shift_reg <= 0;
    end else begin
        state <= next_state;
    end
end

// Lógica de transición de estado
always @(*) begin
    next_state = state;
    case (state)
        IDLE: begin
            if (start) next_state = PREPARE;
        end
        PREPARE: begin
            shift_reg = {2'b01, operation ? 2'b10 : 2'b01, phy_addr, reg_addr, 2'b10, write_data}; // Configuración dependiendo de la operación
            bit_count = 31; // Preparar contador de bits
            next_state = SEND;
        end
        SEND: begin
            if (bit_count == -1) next_state = operation ? RECEIVE : FINISH; // Pasar a recibir si es lectura
        end
        RECEIVE: begin
            if (bit_count == -1) next_state = FINISH;
        end
        FINISH: begin
            next_state = IDLE;
        end
    endcase
end

// Lógica de manejo de datos MDIO
always @(posedge mdc) begin
    if (state == SEND) begin
        mdio_oe <= 1;
        mdio_out <= shift_reg[31];
        shift_reg <= shift_reg << 1;
        bit_count <= bit_count - 1;
    end else if (state == RECEIVE) begin
        mdio_oe <= 0;
        if (bit_count >= 0) begin
            read_data[bit_count] <= mdio_in;
        end
        bit_count <= bit_count - 1;
    end else begin
        mdio_oe <= 0;
    end
end

endmodule

MDIO/controller/controller_tb.v
`timescale 1ns / 1ps
`include "controller/controller.v"

module controller_tb;

    // Inputs
    reg clk;
    reg reset;
    reg mdio_in;
    reg [4:0] phy_addr;
    reg [4:0] reg_addr;
    reg [15:0] write_data;
    reg start;
    reg operation;

    // Outputs
    wire mdio_out;
    wire mdio_oe;
    wire mdc;
    wire [15:0] read_data;
    wire busy;

    // Instancia del controlador MDIO
    mdio_controller uut (
        .clk(clk),
        .reset(reset),
        .mdio_in(mdio_in),
        .mdio_out(mdio_out),
        .mdio_oe(mdio_oe),
        .mdc(mdc),
        .phy_addr(phy_addr),
        .reg_addr(reg_addr),
        .write_data(write_data),
        .read_data(read_data),
        .start(start),
        .operation(operation),
        .busy(busy)
    );

    // Generar señal de reloj
    initial begin
        clk = 0;
        forever #5 clk = ~clk; // Reloj de 100 MHz
    end

    // Inicializar y ejecutar pruebas
    initial begin
        $dumpfile("sim.vcd");
        $dumpvars(0, controller_tb);

        // Inicialización
        reset = 1; mdio_in = 0; start = 0; operation = 0;
        phy_addr = 0; reg_addr = 0; write_data = 0;
        #10 reset = 0;

        // Test de escritura
        phy_addr = 5'b00001;
        reg_addr = 5'b00010;
        write_data = 16'hABCD;
        operation = 0; // Operación de escritura
        start = 1;
        #10; start = 0; // Iniciar la operación

        // Esperar la duración de SEND
        #650; // 640 ns para la transacción + 10 ns de margen

        // Test de lectura
        #20; // Tiempo antes de iniciar la siguiente transacción
        phy_addr = 5'b00011;
        reg_addr = 5'b00100;
        operation = 1; // Operación de lectura
        start = 1;
        #10; start = 0;

        // Esperar la duración de SEND + RECEIVE
        #1290; // (640 ns * 2) para SEND + RECEIVE + 10 ns de margen

        // Conclusión
        #50; // Tiempo adicional antes de finalizar la simulación
        $display("Simulación completada.");
        $finish;
    end

    // Monitoreo de señales para depuración
    initial begin
        $monitor("Time = %t, Operation = %b, Busy = %b, Read Data = %h",
                 $time, operation, busy, read_data);
    end

endmodule

MDIO/sim.vcd
$date
	Tue Jun 11 20:50:34 2024
$end
$version
	Icarus Verilog
$end
$timescale
	1ps
$end
$scope module controller_tb $end
$var wire 16 ! read_data [15:0] $end
$var wire 1 " mdio_out $end
$var wire 1 # mdio_oe $end
$var wire 1 $ mdc $end
$var wire 1 % busy $end
$var reg 1 & clk $end
$var reg 1 ' mdio_in $end
$var reg 1 ( operation $end
$var reg 5 ) phy_addr [4:0] $end
$var reg 5 * reg_addr [4:0] $end
$var reg 1 + reset $end
$var reg 1 , start $end
$var reg 16 - write_data [15:0] $end
$scope module uut $end
$var wire 1 & clk $end
$var wire 1 ' mdio_in $end
$var wire 1 ( operation $end
$var wire 5 . phy_addr [4:0] $end
$var wire 5 / reg_addr [4:0] $end
$var wire 1 + reset $end
$var wire 1 , start $end
$var wire 16 0 write_data [15:0] $end
$var reg 1 % busy $end
$var reg 1 $ mdc $end
$var reg 1 # mdio_oe $end
$var reg 1 " mdio_out $end
$var reg 16 1 read_data [15:0] $end
$var reg 32 2 shift_reg [31:0] $end
$var integer 32 3 bit_count [31:0] $end
$var integer 32 4 next_state [31:0] $end
$var integer 32 5 state [31:0] $end
$upscope $end
$upscope $end
$enddefinitions $end
#0
$dumpvars
b0 5
b0 4
bx 3
bx 2
bx 1
b0 0
b0 /
b0 .
b0 -
0,
1+
b0 *
b0 )
0(
0'
0&
x%
x$
x#
x"
bx !
$end
#5000
0$
b0 2
b0 !
b0 1
0"
0#
0%
1&
#10000
b1 4
0&
1,
b1010101111001101 -
b1010101111001101 0
b10 *
b10 /
b1 )
b1 .
0+
#15000
b10 4
b11111 3
b1010000100010101010101111001101 2
b1 5
1$
1&
#20000
b10 4
0&
0,
#25000
0$
b10 5
1&
#30000
0&
#35000
b11110 3
b10100001000101010101011110011010 2
1#
1$
1&
#40000
0&
#45000
0$
1&
#50000
0&
#55000
b11101 3
b1000010001010101010111100110100 2
1"
1$
1&
#60000
0&
#65000
0$
1&
#70000
0&
#75000
b11100 3
b10000100010101010101111001101000 2
0"
1$
1&
#80000
0&
#85000
0$
1&
#90000
0&
#95000
b11011 3
b1000101010101011110011010000 2
1"
1$
1&
#100000
0&
#105000
0$
1&
#110000
0&
#115000
b11010 3
b10001010101010111100110100000 2
0"
1$
1&
#120000
0&
#125000
0$
1&
#130000
0&
#135000
b11001 3
b100010101010101111001101000000 2
1$
1&
#140000
0&
#145000
0$
1&
#150000
0&
#155000
b11000 3
b1000101010101011110011010000000 2
1$
1&
#160000
0&
#165000
0$
1&
#170000
0&
#175000
b10111 3
b10001010101010111100110100000000 2
1$
1&
#180000
0&
#185000
0$
1&
#190000
0&
#195000
b10110 3
b10101010101111001101000000000 2
1"
1$
1&
#200000
0&
#205000
0$
1&
#210000
0&
#215000
b10101 3
b101010101011110011010000000000 2
0"
1$
1&
#220000
0&
#225000
0$
1&
#230000
0&
#235000
b10100 3
b1010101010111100110100000000000 2
1$
1&
#240000
0&
#245000
0$
1&
#250000
0&
#255000
b10011 3
b10101010101111001101000000000000 2
1$
1&
#260000
0&
#265000
0$
1&
#270000
0&
#275000
b10010 3
b1010101011110011010000000000000 2
1"
1$
1&
#280000
0&
#285000
0$
1&
#290000
0&
#295000
b10001 3
b10101010111100110100000000000000 2
0"
1$
1&
#300000
0&
#305000
0$
1&
#310000
0&
#315000
b10000 3
b1010101111001101000000000000000 2
1"
1$
1&
#320000
0&
#325000
0$
1&
#330000
0&
#335000
b1111 3
b10101011110011010000000000000000 2
0"
1$
1&
#340000
0&
#345000
0$
1&
#350000
0&
#355000
b1110 3
b1010111100110100000000000000000 2
1"
1$
1&
#360000
0&
#365000
0$
1&
#370000
0&
#375000
b1101 3
b10101111001101000000000000000000 2
0"
1$
1&
#380000
0&
#385000
0$
1&
#390000
0&
#395000
b1100 3
b1011110011010000000000000000000 2
1"
1$
1&
#400000
0&
#405000
0$
1&
#410000
0&
#415000
b1011 3
b10111100110100000000000000000000 2
0"
1$
1&
#420000
0&
#425000
0$
1&
#430000
0&
#435000
b1010 3
b1111001101000000000000000000000 2
1"
1$
1&
#440000
0&
#445000
0$
1&
#450000
0&
#455000
b1001 3
b11110011010000000000000000000000 2
0"
1$
1&
#460000
0&
#465000
0$
1&
#470000
0&
#475000
b1000 3
b11100110100000000000000000000000 2
1"
1$
1&
#480000
0&
#485000
0$
1&
#490000
0&
#495000
b111 3
b11001101000000000000000000000000 2
1$
1&
#500000
0&
#505000
0$
1&
#510000
0&
#515000
b110 3
b10011010000000000000000000000000 2
1$
1&
#520000
0&
#525000
0$
1&
#530000
0&
#535000
b101 3
b110100000000000000000000000000 2
1$
1&
#540000
0&
#545000
0$
1&
#550000
0&
#555000
b100 3
b1101000000000000000000000000000 2
0"
1$
1&
#560000
0&
#565000
0$
1&
#570000
0&
#575000
b11 3
b11010000000000000000000000000000 2
1$
1&
#580000
0&
#585000
0$
1&
#590000
0&
#595000
b10 3
b10100000000000000000000000000000 2
1"
1$
1&
#600000
0&
#605000
0$
1&
#610000
0&
#615000
b1 3
b1000000000000000000000000000000 2
1$
1&
#620000
0&
#625000
0$
1&
#630000
0&
#635000
b0 3
b10000000000000000000000000000000 2
0"
1$
1&
#640000
0&
#645000
0$
1&
#650000
0&
#655000
b100 4
b11111111111111111111111111111111 3
b0 2
1"
1$
1&
#660000
0&
#665000
b0 4
0$
b100 5
1&
#670000
0&
#675000
0#
b0 5
1$
1&
#680000
0&
#685000
0$
1&
#690000
b1 4
0&
1,
1(
b100 *
b100 /
b11 )
b11 .
#695000
b10 4
b11111 3
b1100001100100101010101111001101 2
b1 5
1$
1&
#700000
b10 4
0&
0,
#705000
0$
b10 5
1&
#710000
0&
#715000
b11110 3
b11000011001001010101011110011010 2
0"
1#
1$
1&
#720000
0&
#725000
0$
1&
#730000
0&
#735000
b11101 3
b10000110010010101010111100110100 2
1"
1$
1&
#740000
0&
#745000
0$
1&
#750000
0&
#755000
b11100 3
b1100100101010101111001101000 2
1$
1&
#760000
0&
#765000
0$
1&
#770000
0&
#775000
b11011 3
b11001001010101011110011010000 2
0"
1$
1&
#780000
0&
#785000
0$
1&
#790000
0&
#795000
b11010 3
b110010010101010111100110100000 2
1$
1&
#800000
0&
#805000
0$
1&
#810000
0&
#815000
b11001 3
b1100100101010101111001101000000 2
1$
1&
#820000
0&
#825000
0$
1&
#830000
0&
#835000
b11000 3
b11001001010101011110011010000000 2
1$
1&
#840000
0&
#845000
0$
1&
#850000
0&
#855000
b10111 3
b10010010101010111100110100000000 2
1"
1$
1&
#860000
0&
#865000
0$
1&
#870000
0&
#875000
b10110 3
b100101010101111001101000000000 2
1$
1&
#880000
0&
#885000
0$
1&
#890000
0&
#895000
b10101 3
b1001010101011110011010000000000 2
0"
1$
1&
#900000
0&
#905000
0$
1&
#910000
0&
#915000
b10100 3
b10010101010111100110100000000000 2
1$
1&
#920000
0&
#925000
0$
1&
#930000
0&
#935000
b10011 3
b101010101111001101000000000000 2
1"
1$
1&
#940000
0&
#945000
0$
1&
#950000
0&
#955000
b10010 3
b1010101011110011010000000000000 2
0"
1$
1&
#960000
0&
#965000
0$
1&
#970000
0&
#975000
b10001 3
b10101010111100110100000000000000 2
1$
1&
#980000
0&
#985000
0$
1&
#990000
0&
#995000
b10000 3
b1010101111001101000000000000000 2
1"
1$
1&
#1000000
0&
#1005000
0$
1&
#1010000
0&
#1015000
b1111 3
b10101011110011010000000000000000 2
0"
1$
1&
#1020000
0&
#1025000
0$
1&
#1030000
0&
#1035000
b1110 3
b1010111100110100000000000000000 2
1"
1$
1&
#1040000
0&
#1045000
0$
1&
#1050000
0&
#1055000
b1101 3
b10101111001101000000000000000000 2
0"
1$
1&
#1060000
0&
#1065000
0$
1&
#1070000
0&
#1075000
b1100 3
b1011110011010000000000000000000 2
1"
1$
1&
#1080000
0&
#1085000
0$
1&
#1090000
0&
#1095000
b1011 3
b10111100110100000000000000000000 2
0"
1$
1&
#1100000
0&
#1105000
0$
1&
#1110000
0&
#1115000
b1010 3
b1111001101000000000000000000000 2
1"
1$
1&
#1120000
0&
#1125000
0$
1&
#1130000
0&
#1135000
b1001 3
b11110011010000000000000000000000 2
0"
1$
1&
#1140000
0&
#1145000
0$
1&
#1150000
0&
#1155000
b1000 3
b11100110100000000000000000000000 2
1"
1$
1&
#1160000
0&
#1165000
0$
1&
#1170000
0&
#1175000
b111 3
b11001101000000000000000000000000 2
1$
1&
#1180000
0&
#1185000
0$
1&
#1190000
0&
#1195000
b110 3
b10011010000000000000000000000000 2
1$
1&
#1200000
0&
#1205000
0$
1&
#1210000
0&
#1215000
b101 3
b110100000000000000000000000000 2
1$
1&
#1220000
0&
#1225000
0$
1&
#1230000
0&
#1235000
b100 3
b1101000000000000000000000000000 2
0"
1$
1&
#1240000
0&
#1245000
0$
1&
#1250000
0&
#1255000
b11 3
b11010000000000000000000000000000 2
1$
1&
#1260000
0&
#1265000
0$
1&
#1270000
0&
#1275000
b10 3
b10100000000000000000000000000000 2
1"
1$
1&
#1280000
0&
#1285000
0$
1&
#1290000
0&
#1295000
b1 3
b1000000000000000000000000000000 2
1$
1&
#1300000
0&
#1305000
0$
1&
#1310000
0&
#1315000
b0 3
b10000000000000000000000000000000 2
0"
1$
1&
#1320000
0&
#1325000
0$
1&
#1330000
0&
#1335000
b11 4
b11111111111111111111111111111111 3
b0 2
1"
1$
1&
#1340000
0&
#1345000
b100 4
0$
b11 5
1&
#1350000
0&
#1355000
0#
b0 4
b100 5
1$
1&
#1360000
0&
#1365000
0$
b0 5
1&
#1370000
0&
#1375000
1$
1&
#1380000
0&
#1385000
0$
1&
#1390000
0&
#1395000
1$
1&
#1400000
0&
#1405000
0$
1&
#1410000
0&
#1415000
1$
1&
#1420000
0&
#1425000
0$
1&
#1430000
0&
#1435000
1$
1&
#1440000
0&
#1445000
0$
1&
#1450000
0&
#1455000
1$
1&
#1460000
0&
#1465000
0$
1&
#1470000
0&
#1475000
1$
1&
#1480000
0&
#1485000
0$
1&
#1490000
0&
#1495000
1$
1&
#1500000
0&
#1505000
0$
1&
#1510000
0&
#1515000
1$
1&
#1520000
0&
#1525000
0$
1&
#1530000
0&
#1535000
1$
1&
#1540000
0&
#1545000
0$
1&
#1550000
0&
#1555000
1$
1&
#1560000
0&
#1565000
0$
1&
#1570000
0&
#1575000
1$
1&
#1580000
0&
#1585000
0$
1&
#1590000
0&
#1595000
1$
1&
#1600000
0&
#1605000
0$
1&
#1610000
0&
#1615000
1$
1&
#1620000
0&
#1625000
0$
1&
#1630000
0&
#1635000
1$
1&
#1640000
0&
#1645000
0$
1&
#1650000
0&
#1655000
1$
1&
#1660000
0&
#1665000
0$
1&
#1670000
0&
#1675000
1$
1&
#1680000
0&
#1685000
0$
1&
#1690000
0&
#1695000
1$
1&
#1700000
0&
#1705000
0$
1&
#1710000
0&
#1715000
1$
1&
#1720000
0&
#1725000
0$
1&
#1730000
0&
#1735000
1$
1&
#1740000
0&
#1745000
0$
1&
#1750000
0&
#1755000
1$
1&
#1760000
0&
#1765000
0$
1&
#1770000
0&
#1775000
1$
1&
#1780000
0&
#1785000
0$
1&
#1790000
0&
#1795000
1$
1&
#1800000
0&
#1805000
0$
1&
#1810000
0&
#1815000
1$
1&
#1820000
0&
#1825000
0$
1&
#1830000
0&
#1835000
1$
1&
#1840000
0&
#1845000
0$
1&
#1850000
0&
#1855000
1$
1&
#1860000
0&
#1865000
0$
1&
#1870000
0&
#1875000
1$
1&
#1880000
0&
#1885000
0$
1&
#1890000
0&
#1895000
1$
1&
#1900000
0&
#1905000
0$
1&
#1910000
0&
#1915000
1$
1&
#1920000
0&
#1925000
0$
1&
#1930000
0&
#1935000
1$
1&
#1940000
0&
#1945000
0$
1&
#1950000
0&
#1955000
1$
1&
#1960000
0&
#1965000
0$
1&
#1970000
0&
#1975000
1$
1&
#1980000
0&
#1985000
0$
1&
#1990000
0&
#1995000
1$
1&
#2000000
0&
#2005000
0$
1&
#2010000
0&
#2015000
1$
1&
#2020000
0&
#2025000
0$
1&
#2030000
0&
#2035000
1$
1&
